Workbook

Sheet 项目总览与综合报价
A1: 四川省川剧院与多场景低延迟实时翻译智能耳机 · 全栈软硬件与AI算力部署综合成本表
A2: 【最终代一体化解决方案】涵盖 10+多语种实时同传硬件耳机研发、全栈软件多端App、开源AI模型算法定制及私有化GPU服务器集群
A4: 项目基本信息与规格基准
A5: 项目名称 | B5: 低延迟多语种实时翻译智能耳机（最终代）全栈研发与算力部署 | E5: 委托/应用单位 | F5: 四川省川剧院 / 商业集团大卖场 / 跨国文旅
A6: 报价编制日期 | B6: 2026年08月28日 | E6: 方案版本与周期 | F6: 终代完整商用版 (V3.0 Final) / 约 3~3.5 个月
A7: 核心硬件定义 | B7: 川剧文创双模智能翻译耳机 (带触控屏智能仓+骨传导ENC) | E7: 核心AI与模型 | F7: SenseVoice + Qwen2.5/NLLB-200 + CosyVoice2.0 + 4U GPU节点
A8: 工程预算与成本模块总览 (包含软硬件、模具、AI算法与服务器)
A9: 序号 | B9: 工程成本板块名称 | C9: 核心研制内容与交付目标概述 | D9: 参考工期 | E9: 含税报价 (RMB) | F9: 预算占比 | G9: 关联明细工作表索引
A10: 1 | B10: 一、专属智能翻译耳机硬件研发与模具 (NRE) | C10: 包含外观ID/结构MD设计、旗舰BT5.4电路EE、智能触控仓、固件开发及全套精密注塑模具 | D10: 65 工作日 | E10: =硬件研发与开模明细!F12 -> 317000 | F10: =E10/E17 -> 0.28623025 | G10: 参阅 Sheet 2《硬件研发与开模明细》
A11: 2 | B11: 二、硬件工程打样、声学调音与权威认证 (SRRC) | C11: 包含CNC手板、SMT样板、消音室B&K声学降噪曲线调优、测试治具及国家SRRC/CE核准认证规费 | D11: 20 工作日 | E11: =硬件研发与开模明细!F18 -> 106000 | F11: =E11/E17 -> 0.095711061 | G11: 参阅 Sheet 2《硬件研发与开模明细》
A12: 3 | B12: 三、全栈软件系统与多端应用研发 (App/Web/Cloud) | C12: 包含iOS/Android跨平台App、川剧院沉浸同传、大卖场商超面对面翻译、WebRTC低延迟流媒体网关及后台 | D12: 50 工作日 | E12: =软件与多端系统研发明细!F15 -> 317500 | F12: =E12/E17 -> 0.28668172 | G12: 参阅 Sheet 3《软件与多端系统研发明细》
A13: 4 | B13: 四、AI 开源最佳模型算法定制与工程加速 | C13: 包含 SenseVoice ASR + Qwen2.5/NLLB-200 实时翻译 + CosyVoice2.0 零样本名角音色克隆与 TRT-LLM 加速 | D13: 30 工作日 | E13: =AI模型算法与算力服务器部署!F8 -> 117000 | F13: =E13/E17 -> 0.10564334 | G13: 参阅 Sheet 4《AI模型算法与算力服务器部署》
A14: 5 | B14: 五、私有化 AI 算力 GPU 服务器物理硬件与集群部署 | C14: 包含 4U 企业级双路服务器整机、2 张专业级 NVIDIA GPU 推理加速卡 (48G~96G 显存) 及 Triton 调度集群 | D14: 15 工作日 | E14: =AI模型算法与算力服务器部署!F13 -> 129000 | F14: =E14/E17 -> 0.11647856 | G14: 参阅 Sheet 4《AI模型算法与算力服务器部署》
A15: 6 | B15: 六、首批全功能智能翻译耳机工程试产 (200套) | C15: 包含 200 套完整功能智能耳机+触控充电仓生产物料、试产组装全检、川剧脸谱彩绘及精装文创礼盒 | D15: 25 工作日 | E15: ='首批耳机试产费用(200套)'!F10 -> 76000 | F15: =E15/E17 -> 0.068623025 | G15: 参阅 Sheet 5《首批耳机试产费用(200套)》
A16: 7 | B16: 七、系统现场部署联调、培训与首年运维保修 | C16: 包含川剧院大剧场与大卖场实地弱电/网络/音频联调、操作培训、12个月全套软硬件免费保修与技术支持 | D16: 全周期 | E16: 45000 | F16: =E16/E17 -> 0.040632054 | G16: 包含技术团队现场驻场与1年运维服务
A17: 项目工程综合投资总预算 (含税 RMB) | E17: =SUM(E10:E16) -> 1107500 | F17: =SUM(F10:F16) -> 1 | G17: 包含全套软硬件产权、模具所有权、GPU服务器及200套现货样机
A19: 交付物清单、知识产权与商务付款阶段
A20: 1. 商业付款阶段 | B20: 首期款 35%（合同生效与方案确认后启动软硬件）；中期款 30%（模具 T0 试模与软件 Beta 联调完成）；试产验收款 25%（首批 200 套样机与 GPU 服务器交付现场测试合格）；质保金 10%（系统平稳运行满 1 年后付清）。
A21: 2. 硬件交付成果 | B21: 包含全套 3D STEP 结构图、原理图/PCB Gerber 文件、固件源码与烧录工具、全套塑胶钢模所有权、国家 SRRC 核准证书、200 套全功能包装样机。
A22: 3. 软件与AI交付物 | B22: 包含移动端 App (iOS/Android) 完整源码、WebRTC 媒体服务源码、Admin 后台源码、SenseVoice/Qwen2.5/CosyVoice 模型权重与微调代码、Docker 容器镜像。
A23: 4. 服务器物理硬件 | B23: 交付包含 4U 双路高性能 GPU 服务器整机一台（含 2 张专业级 NVIDIA GPU 算力卡），现场完成系统部署与推理性能压力测试验收。
A24: 5. 运维与技术保障 | B24: 提供自验收之日起 12 个月免费技术支持与软件缺陷修复，提供现场技术人员操作培训，终身提供系统架构扩容技术咨询。

Sheet 硬件研发与开模明细
A1: 最终代低延迟多语种翻译智能耳机 · 硬件工程研发与精密开模费用明细
A2: 包含旗舰级 BT5.4/LE Audio 主控、骨传导 VPU+双麦 ENC、智能触控充电仓设计、高淬火精密钢模与权威无线电认证
A3: 工程编号 | B3: 研发/开模子项 | C3: 详细技术指标与工程实施要点 | D3: 数量/单位 | E3: 基准单价 (元) | F3: 含税小计 (RMB) | G3: 交付成果与验收标准
A4: HW-01 | B4: 1. 工业设计 ID (耳机+智能仓) | C4: 川剧脸谱非遗元素与轻奢科技结合，人体工学开放式/半入耳结构，带触控屏智能仓外观建模与CMF材质定义 | D4: 1 | E4: 28000 | F4: =D4*E4 -> 28000 | G4: 3D渲染图、配色CMF文档、手感样机模型
A5: HW-02 | B5: 2. 结构工程 MD 设计 | C5: 超轻量钛合金记忆钢丝骨架、双麦风道降噪声学腔体、智能仓转轴与触控屏堆叠结构、IP54防水密封 | D5: 1 | E5: 35000 | F5: =D5*E5 -> 35000 | G5: 3D STEP 完整结构图纸、2D工程开模图
A6: HW-03 | B6: 3. 硬件电路 EE (旗舰BT5.4方案) | C6: BES2700 / QCC5181 旗舰双模主控（支持LE Audio/LC3超低延迟 <20ms）、双反馈高信噪比硅麦+骨传导VPU电路、PMIC | D6: 1 | E6: 38000 | F6: =D6*E6 -> 38000 | G6: 原理图、8层高精PCB Gerber、BOM物料表
A7: HW-04 | B7: 4. 智能充电仓 EE 电路设计 | C7: 智能仓独立 MCU 主控电路、1.44寸触控 OLED 显示屏驱动电路、霍尔开关检测、无线充电 Qi 接收芯片 | D7: 1 | E7: 25000 | F7: =D7*E7 -> 25000 | G7: 智能仓主板原理图与PCB Gerber文件
A8: HW-05 | B8: 5. 嵌入式固件 Firmware 开发 | C8: LC3/Opus 低延迟流式传输固件、Auracast 剧院广播接收协议、触控屏双向交互协议、低功耗省电算法、OTA升级 | D8: 1 | E8: 36000 | F8: =D8*E8 -> 36000 | G8: 固件全套源码、量产HEX镜像、OTA升级包
A9: HW-06 | B9: 6. 耳机外壳精密塑胶模具 | C9: 左右耳机壳精密注塑模具（长寿命高耐磨 S136 淬火钢，保证 10 万模次无毛边高精度公差 ±0.02mm） | D9: 1 | E9: 58000 | F9: =D9*E9 -> 58000 | G9: 左右耳机注塑钢模 1 套
A10: HW-07 | B10: 7. 智能仓及机构件精密模具 | C10: 充电仓上下盖、转轴精密五金件注塑模、触控屏视窗高透模具、硅胶亲肤耳翼模具 | D10: 1 | E10: 75000 | F10: =D10*E10 -> 75000 | G10: 充电仓及五金配件注塑模 1 套
A11: HW-08 | B11: 8. 模具试模修模与表面工艺 | C11: T0/T1/T2 试模注塑检讨、模具高光晒纹/咬花处理、耐磨抗指纹 UV 喷涂工艺调优 | D11: 1 | E11: 22000 | F11: =D11*E11 -> 22000 | G11: 试模调优报告、合格外壳样件
A12: 小计一：硬件研发与精密模具开发费用 (NRE) | D12: - | E12: - | F12: =SUM(F4:F11) -> 317000 | G12: 包含ID/MD/EE/固件设计与全套注塑模具
A13: 二、工程手板打样、声学校准与权威认证
A14: HW-09 | B14: 9. 3D/CNC 结构手板打样 | C14: 高精度五轴 CNC 铝合金/钛合金与 SLA 光敏树脂结构手板打样（10套），用于气密性与人体工学测试 | D14: 10 | E14: 1500 | F14: =D14*E14 -> 15000 | G14: 合格结构外观工程手板 10 套
A15: HW-10 | B15: 10. SMT 电路样板打样与调纤 | C15: 高精多层 PCB 样板打样、BOM器件采购、SMT贴片（20板），射频天线矢量网络分析与阻抗匹配 | D15: 20 | E15: 900 | F15: =D15*E15 -> 18000 | G15: 功能测试电路样板 20 板
A16: HW-11 | B16: 11. 消音室声学调音与治具 | C16: 专业消音室 B&K 人头人工耳频响曲线调优、ENC 双麦降噪算法调校、量产声学与RF测试治具制作 | D16: 1 | E16: 28000 | F16: =D16*E16 -> 28000 | G16: 声学调音曲线报告、测试治具 1 套
A17: HW-12 | B17: 12. 权威认证规费 (SRRC/CE/IP54) | C17: 国家无线电管理局 SRRC 型号核准认证、欧盟 CE-RED 认证、FCC-ID 备案、IP54 级防尘防水检测报告 | D17: 1 | E17: 45000 | F17: =D17*E17 -> 45000 | G17: 国家 SRRC 证书、CE/FCC/IP54 检验报告
A18: 小计二：打样调试、声学治具与权威认证费用 | D18: - | E18: - | F18: =SUM(F14:F17) -> 106000 | G18: 包含CNC手板、SMT样板、声学校准与SRRC/CE认证
A19: 硬件工程研发、模具与认证总计 (含税 RMB) | F19: =F12+F18 -> 423000 | G19: 研发开模 + 声学工程 + 权威资质核准

Sheet 软件与多端系统研发明细
A1: 跨场景低延迟多语种实时翻译系统 · 软件与多端 App 研发明细表
A2: 涵盖移动端多场景同传 App (iOS/Android)、川剧院观戏小程序/Web同传、大卖场商超面对面对讲、WebRTC低延迟音频流网关及微服务中台
A3: 模块编号 | B3: 软件系统/功能模块 | C3: 详细功能特性与核心技术实现指标 | D3: 预估工时 (人天) | E3: 基准单价 (元/人天) | F3: 含税小计 (RMB) | G3: 技术交付物与交付标准
A4: SW-01 | B4: 1. 跨平台多语种翻译 App (iOS/Android) | C4: Flutter/React Native 架构，支持蓝牙 BLE/Classic 双通道连接、低延迟音频流收发、波形动态可视化 | D4: 18 | E4: 2200 | F4: =D4*E4 -> 39600 | G4: iOS & Android 客户端安装包与全套源码
A5: SW-02 | B5: 2. 【场景一】川剧院沉浸导览与戏曲同传 | C5: 《皮金滚灯》等川剧经典戏段实时双语/多语字幕滚动、名角音色原声+同传解说混合推流、文博展品蓝牙自动感应导览 | D5: 12 | E5: 2200 | F5: =D5*E5 -> 26400 | G5: 川剧院定制剧场导览与字幕同步模块
A6: SW-03 | B6: 3. 【场景二】大卖场/商超面对面双向对讲 | C6: 一人一耳双向即时对讲模式，自动分离双方声轨，低延迟互译并自动抑制嘈杂卖场环境底噪，支持常用商品术语快捷翻译 | D6: 14 | E6: 2200 | F6: =D6*E6 -> 30800 | G6: 商超零售双向对讲模式专用组件
A7: SW-04 | B7: 4. 【场景三】多语种国际会议与群聊同传 | C7: 多人多语种跨国群聊房间，语音实时转写多国文字并同传分发，支持会议纪要中英双语即时导出与录音归档 | D7: 12 | E7: 2200 | F7: =D7*E7 -> 26400 | G7: 多方群聊同传与会议纪要导出系统
A8: SW-05 | B8: 5. 东南亚小语种与主流语言库引擎 (16+语种) | C8: 支持中、英、日、韩、法、西、俄、阿，以及东南亚小语种（泰、越、印尼、马来、缅甸、高棉/柬埔寨、菲律宾语等）精准互译 | D8: 16 | E8: 2500 | F8: =D8*E8 -> 40000 | G8: 多语种国际化字典与实时分流适配引擎
A9: SW-06 | B9: 6. WebRTC 超低延迟音频流媒体网关 | C9: Go/C++ 实现高并发 WebRTC/Opus 音频网关，毫秒级音频流分片传输（端到端链路延迟优化至 <100ms） | D9: 15 | E9: 2500 | F9: =D9*E9 -> 37500 | G9: WebRTC 媒体流转发网关服务端源码
A10: SW-07 | B10: 7. 端侧离线轻量翻译包与断网容灾 | C10: 内置端侧轻量 NPU 离线翻译模型（支持中/英/日/韩/泰/越无网络环境下基础对话实时互译，网络中断无缝切换） | D10: 12 | E10: 2500 | F10: =D10*E10 -> 30000 | G10: 端侧离线翻译引擎包及 SDK
A11: SW-08 | B11: 8. 文创非遗数字资产与 AI 旅拍 | C11: 川剧 AI 华服试穿、名角同框合影 (Gemini 多模态集成)、非遗脸谱纹样数字资产库与 IP 数字藏品铸造中心 | D11: 10 | E11: 2000 | F11: =D11*E11 -> 20000 | G11: 数字资产库、AI 旅拍 API 代理服务
A12: SW-09 | B12: 9. 云端高并发业务微服务架构 (FastAPI/Go) | C12: 微服务架构、JWT 多租户鉴权、设备唯一 MAC 绑定、动态流控与负载均衡、高并发 SQL/Redis 缓存设计 | D12: 14 | E12: 2200 | F12: =D12*E12 -> 30800 | G12: 后端核心业务微服务全套工程源码
A13: SW-10 | B13: 10. 综合管理后台系统 (Admin Web UI) | C13: 剧场剧目排期管理、商超设备租借与资产巡检管理、AI 翻译流量统计看板、多语种术语词库管理后台 | D13: 12 | E13: 2000 | F13: =D13*E13 -> 24000 | G13: Vue3 / Tailwind 管理后台前端与接口
A14: SW-11 | B14: 11. 生产环境容器化部署与 DevOps | C14: Docker / Kubernetes 自动化容器编排脚本、Nginx 高可用负载均衡、SSL/TLS 证书加固、Prometheus 监控告警 | D14: 6 | E14: 2000 | F14: =D14*E14 -> 12000 | G14: K8s 编排部署文件、CI/CD 自动化流水线
A15: 全栈软件与多端 App 研发费用小计 (含税 RMB) | D15: =SUM(D4:D14) -> 141 | E15: - | F15: =SUM(F4:F14) -> 317500 | G15: 全套移动端 App、WebRTC 媒体服务及后台源码交付

Sheet AI模型算法与算力服务器部署
A1: AI 实时翻译推理大模型定制与私有化 GPU 算力集群配置明细表
A2: 采用业界顶尖开源多语种模型（SenseVoice/Whisper + Qwen2.5/NLLB-200 + CosyVoice2.0）及高性能 GPU 物理服务器搭建低延迟私有化集群
A3: 编号 | B3: AI 算法/算力硬件项目 | C3: 技术规格、选型依据与性能指标 | D3: 数量/配置 | E3: 单价 (元) | F3: 含税小计 (RMB) | G3: 交付形式与性能保证
A4: AI-01 | B4: 1. 流式多语种 ASR 语音识别模型 | C4: SenseVoice-Small (阿里开源, 延迟<100ms) + Faster-Whisper-large-v3-turbo (支持全球100+语言及东南亚小语种) 混合调度 | D4: 1 | E4: 28000 | F4: =D4*E4 -> 28000 | G4: 流式 ASR 微服务、Docker 镜像、延迟<120ms
A5: AI-02 | B5: 2. 低延迟大模型同传翻译 (MT/LLM) | C5: Qwen2.5-7B/14B-Instruct-AWQ (中文/通用语言精译) + NLLB-200 (Meta 200语言专注东南亚小语种) 流式切词微调 | D5: 1 | E5: 35000 | F5: =D5*E5 -> 35000 | G5: TensorRT-LLM / vLLM 加速部署，首字延迟<150ms
A6: AI-03 | B6: 3. 零样本多语种流式 TTS 与名角音色克隆 | C6: CosyVoice 2.0 / F5-TTS 零样本音色克隆，3秒音频克隆川剧名角/特定客服专属音色，支持流式分块输出（Chunk Streaming） | D6: 1 | E6: 32000 | F6: =D6*E6 -> 32000 | G6: 多语种流式 TTS 引擎，端到端合成延迟<120ms
A7: AI-04 | B7: 4. 行业术语库与川剧戏曲文化微调 | C7: 针对川剧戏曲专业名词、文创典故、大卖场零售商品专有名词进行 LoRA 领域指令微调与敏感词合规过滤 | D7: 1 | E7: 22000 | F7: =D7*E7 -> 22000 | G7: 专用领域微调权重包及术语词表
A8: 小计一：AI 模型算法定制、微调与工程加速费用 | D8: - | E8: - | F8: =SUM(F4:F7) -> 117000 | G8: 包含 ASR/MT/TTS 开源模型调优与 vLLM/TRT-LLM 加速
A9: 二、私有化 AI 算力 GPU 服务器物理硬件与集群部署 (私有云方案)
A10: SRV-01 | B10: 5. 4U 专业 AI 推理 GPU 服务器主机 | C10: 双路 AMD EPYC 9354 (64核128线程) / 512GB DDR5 ECC 内存 / 2x 3.84TB 企业级 NVMe SSD (RAID1) / 2000W 冗余白金电源 / 4U 机架式 | D10: 1 | E10: 55000 | F10: =D10*E10 -> 55000 | G10: 企业级高可靠 4U 机架式服务器整机
A11: SRV-02 | B11: 6. 专业级 AI 加速卡 GPU (NVIDIA L40S 48G / RTX 4090D 24G x 2) | C11: 配置 2 张专业大模型推理显卡（总显存 48GB~96GB），支持 FP8/INT4 量化加速，单机可并发承载 80~120 路实时流式同传通道 | D11: 2 | E11: 28000 | F11: =D11*E11 -> 56000 | G11: 原厂正品 GPU 算力卡（含 3 年保修）
A12: SRV-03 | B12: 7. 算力集群调度与 Triton 推理引擎部署 | C12: 基于 Triton Inference Server + vLLM 搭建动态批处理 (Dynamic Batching) 推理集群、K8s 容器调度与 Prometheus 监控体系 | D12: 1 | E12: 18000 | F12: =D12*E12 -> 18000 | G12: 完整算力调度系统、压力测试报告与运维手册
A13: 小计二：私有化 GPU 服务器硬件购置与集群部署费用 | D13: - | E13: - | F13: =SUM(F10:F12) -> 129000 | G13: 包含物理 GPU 服务器整机、双卡算力及私有化调度集群
A14: AI 模型定制与私有化算力服务器总计 (含税 RMB) | F14: =F8+F13 -> 246000 | G14: AI 核心算法资产 + 独立物理 GPU 算力服务器

Sheet 首批耳机试产费用(200套)
A1: 最终代低延迟多语种翻译耳机 · 首批工程试产与文创礼盒包装 (200套)
A2: 用于川剧院首期商用部署、大卖场导购示范网点试点与市场品鉴推广
A3: 物料编号 | B3: 试产材料与工序构成 | C3: 规格标准与加工工艺要求 | D3: 数量 | E3: 单价 (元) | F3: 含税小计 (RMB) | G3: 交付形态
A4: MAT-01 | B4: 1. 旗舰蓝牙双模主板 PCBA | C4: BES2700/QCC5181 方案，高精 8 层沉金 PCB，含 VPU 骨震动传感器与双麦阵列贴片 | D4: 200 | E4: 165 | F4: =D4*E4 -> 33000 | G4: 测试合格 PCBA 主板 200 套
A5: MAT-02 | B5: 2. 智能充电仓主板及触控 OLED 模组 | C5: 含独立 MCU、1.44寸全彩触控 OLED 模组、Type-C 充放电主板与磁吸霍尔排线 | D5: 200 | E5: 75 | F5: =D5*E5 -> 15000 | G5: 智能仓核心显示与控制总成 200 套
A6: MAT-03 | B6: 3. 聚合物高密度安全电池 (耳机+仓) | C6: 耳机 45mAh 钢壳纽扣/针状锂电池 (双只) + 智能仓 600mAh 聚合物安全防爆电池 | D6: 200 | E6: 32 | F6: =D6*E6 -> 6400 | G6: A品高循环电芯 200 套
A7: MAT-04 | B7: 4. 精密注塑外壳与川剧脸谱喷涂 | C7: T1 试模高精塑胶壳体、川剧变脸精美彩绘移印、耐刮擦 UV 保护漆表面处理 | D7: 200 | E7: 48 | F7: =D7*E7 -> 9600 | G7: 全套精美文创外观结构件 200 套
A8: MAT-05 | B8: 5. 试产车间装配、气密/声学全检 | C8: 无尘车间装配组装、超声波焊接、自动化声学测试全检、射频校准与高温老化测试 | D8: 200 | E8: 35 | F8: =D8*E8 -> 7000 | G8: 组装测试合格成品 200 套
A9: MAT-06 | B9: 6. 川剧非遗定制精美礼盒与配件 | C9: 高档天地盖烫金礼盒、定制收纳袋、多规格亲肤硅胶耳塞套、编制充电线、精装说明书 | D9: 200 | E9: 25 | F9: =D9*E9 -> 5000 | G9: 精美成品礼盒包装 200 套
A10: 首批 200 套全功能智能翻译耳机试产总计 (含税 RMB) | D10: 200 | E10: =F10/D10 -> 380 | F10: =SUM(F4:F9) -> 76000 | G10: 包含 200 套完整功能耳机与定制文创礼盒成品交付
